LICENSE
LICENSE.txt
README.md
setup.cfg
setup.py
greatawesomeutils/__init__.py
greatawesomeutils/base_data.py
greatawesomeutils/base_task.py
greatawesomeutils/base_task_no_driver.py
greatawesomeutils/config.py
greatawesomeutils/country_codes.py
greatawesomeutils/enums.py
greatawesomeutils/errors.py
greatawesomeutils/ip_utils.py
greatawesomeutils/lang.py
greatawesomeutils/local_storage.py
greatawesomeutils/relative_path.py
greatawesomeutils/req.py
greatawesomeutils/selenium.py
greatawesomeutils/selenium_driver.py
greatawesomeutils/temp_email.py
greatawesomeutils/threading_utils.py
greatawesomeutils/user_agents.py
greatawesomeutils/window_sizes.py
greatawesomeutils.egg-info/PKG-INFO
greatawesomeutils.egg-info/SOURCES.txt
greatawesomeutils.egg-info/dependency_links.txt
greatawesomeutils.egg-info/top_level.txt