Metadata-Version: 2.1
Name: greatawesomeutils
Version: 0.0.25
Summary: Scraping in python made easy - receive the content you like in just one line of code!
Home-page: https://github.com/joelbarmettlerUZH/Scrapeasy
Download-URL: https://github.com/joelbarmettlerUZH/Scrapeasy/archive/pypi-0_1_3.tar.gz
Author: Joel Barmettler
Author-email: joel.barmettler@uzh.ch
License: MIT
Keywords: scraping,easy,scraper,website,download,links,images,videos
Classifier: Development Status :: 3 - Alpha
Classifier: Intended Audience :: Developers
Classifier: Topic :: Software Development :: Build Tools
Classifier: License :: OSI Approved :: MIT License
Classifier: Programming Language :: Python :: 3
Classifier: Programming Language :: Python :: 3.4
Classifier: Programming Language :: Python :: 3.5
Classifier: Programming Language :: Python :: 3.6
License-File: LICENSE
License-File: LICENSE.txt
